{
  "basics": {
    "name": "Aryaman Srivastav",
    "label": "",
    "image": "",
    "email": "as188@illinois.edu",
    "phone": "",
    "url": "https://blackk100.github.io/",
    "summary": "",
    "location": {
      "address": "",
      "postalCode": "IL 61801",
      "city": "Urbana",
      "countryCode": "US",
      "region": "Illinois"
    }
  },
  "work": [
    {
      "name": "Advanced Blankets and Coolants Laboratory, University of Illinois Urbana-Champaign",
      "position": "Graduate Research Assistant",
      "url": "https://abc.npre.illinois.edu/",
      "startDate": "2023-10-01",
      "endDate": "Present",
      "summary": "Developing a multiphysics computational framework for investigating thermophysical and electrochemical properties of ionic liquids & molten salts."
    },
    {
      "name": "Gas Turbine Research Establishment, Defense Research and Development Organization",
      "position": "Research Intern",
      "url": "https://www.drdo.gov.in/drdo/labs-and-establishments/gas-turbine-research-establishment-gtre",
      "startDate": "1933-01-01",
      "endDate": "1955-01-01",
      "summary": "Developed an algorithm to find the geometry of a supersonic vacuum ejector (fluid vacuum device) using a non-equilibrium working fluid (thermal and chemical non-equilibrium)."
    },
    {
      "name": "HMT Machine Tools Ltd.",
      "position": "Intern",
      "url": "https://www.hmtmachinetools.com/",
      "startDate": "1933-01-01",
      "endDate": "1955-01-01",
      "summary": "Applied design for manufacturing & assembly and geometric dimensioning & tolerancing principles for small parts design."
    }
  ],
  "education": [
    {
      "institution": "University of Illinois Urbana-Champaign",
      "location": "Urbana, USA",
      "url": "https://illinois.edu/",
      "area": "Aerospace Engineering",
      "studyType": "M.S.",
      "startDate": "2023-08-01",
      "endDate": "Present",
      "score": "3.46"
    },
    {
      "institution": "Manipal Institute of Technology",
      "location": "Manipal, India",
      "url": "https://www.manipal.edu/mit.html",
      "area": "Mechanical Engineering",
      "studyType": "B.Tech.",
      "startDate": "2019-08-01",
      "endDate": "2023-07-01",
      "score": "8.45"
    }
  ],
  "skills": [
    {
      "name": "Programming Languages",
      "level": "Master",
      "icon": "fa-solid fa-hashtag",
      "keywords": [
        "C++",
        "C",
        "Python",
        "MATLAB",
        "R",
        "Fortran"
      ]
    },
    {
      "name": "Analysis Software",
      "level": "Master",
      "icon": "fa-solid fa-hashtag",
      "keywords": [
        "OpenFOAM",
        "COMSOL",
        "Ansys Fluent",
        "Ansys Mechanical",
        "MOOSE",
        "ABAQUS",
        "HyperMesh",
        "LabVIEW",
        "Simulink"
      ]
    },
    {
      "name": "Design Software",
      "level": "Master",
      "icon": "fa-solid fa-hashtag",
      "keywords": [
        "Siemens NX",
        "CATIA",
        "SolidWorks",
        "AutoCAD",
        "Fusion 360"
      ]
    }
  ],
  "languages": [
    {
      "language": "English",
      "fluency": "Fluent",
      "icon": ""
    },
    {
      "language": "Hindi",
      "fluency": "Native speaker",
      "icon": ""
    }
  ]
}
